LICENSE
README.md
README.rst
requirements.txt
setup.cfg
setup.py
test-requirements.txt
src/pyopnsense2/__init__.py
src/pyopnsense2/client.py
src/pyopnsense2/core_captiveportal.py
src/pyopnsense2/core_core.py
src/pyopnsense2/core_cron.py
src/pyopnsense2/core_diagnostics.py
src/pyopnsense2/core_firewall.py
src/pyopnsense2/core_firmware.py
src/pyopnsense2/core_ids.py
src/pyopnsense2/core_interfaces.py
src/pyopnsense2/core_ipsec.py
src/pyopnsense2/core_menu.py
src/pyopnsense2/core_monit.py
src/pyopnsense2/core_openvpn.py
src/pyopnsense2/core_proxy.py
src/pyopnsense2/core_routes.py
src/pyopnsense2/core_syslog.py
src/pyopnsense2/core_trafficshaper.py
src/pyopnsense2/core_unbound.py
src/pyopnsense2/exceptions.py
src/pyopnsense2/plugins_acmeclient.py
src/pyopnsense2/plugins_backup.py
src/pyopnsense2/plugins_bind.py
src/pyopnsense2/plugins_chrony.py
src/pyopnsense2/plugins_cicap.py
src/pyopnsense2/plugins_clamav.py
src/pyopnsense2/plugins_collectd.py
src/pyopnsense2/plugins_diagnostics.py
src/pyopnsense2/plugins_dnscryptproxy.py
src/pyopnsense2/plugins_firewall.py
src/pyopnsense2/plugins_freeradius.py
src/pyopnsense2/plugins_ftpproxy.py
src/pyopnsense2/plugins_gridexample.py
src/pyopnsense2/plugins_haproxy.py
src/pyopnsense2/plugins_helloworld.py
src/pyopnsense2/plugins_hwprobe.py
src/pyopnsense2/plugins_iperf.py
src/pyopnsense2/plugins_lldpd.py
src/pyopnsense2/plugins_maltrail.py
src/pyopnsense2/plugins_mdnsrepeater.py
src/pyopnsense2/plugins_muninnode.py
src/pyopnsense2/plugins_netdata.py
src/pyopnsense2/plugins_netsnmp.py
src/pyopnsense2/plugins_nginx.py
src/pyopnsense2/plugins_nodeexporter.py
src/pyopnsense2/plugins_nrpe.py
src/pyopnsense2/plugins_ntopng.py
src/pyopnsense2/plugins_nut.py
src/pyopnsense2/plugins_openconnect.py
src/pyopnsense2/plugins_postfix.py
src/pyopnsense2/plugins_proxysso.py
src/pyopnsense2/plugins_proxyuseracl.py
src/pyopnsense2/plugins_quagga.py
src/pyopnsense2/plugins_redis.py
src/pyopnsense2/plugins_relayd.py
src/pyopnsense2/plugins_rspamd.py
src/pyopnsense2.egg-info/PKG-INFO
src/pyopnsense2.egg-info/SOURCES.txt
src/pyopnsense2.egg-info/dependency_links.txt
src/pyopnsense2.egg-info/pbr.json
src/pyopnsense2.egg-info/requires.txt
src/pyopnsense2.egg-info/top_level.txt